hlner/__init__.py
hlner/main.py
hlner-0.1.0.dist-info/entry_points.txt
hlner-0.1.0.dist-info/WHEEL
hlner-0.1.0.dist-info/METADATA
hlner-0.1.0.dist-info/RECORD
