Metadata-Version: 2.1
Name: hlner
Version: 0.1.0
Summary: Create and remove hard directory links
Author: mush42
Author-email: musharraf.omer@gmail.com
Requires-Python: >=3.9,<4.0
Classifier: Programming Language :: Python :: 3
Classifier: Programming Language :: Python :: 3.9
Classifier: Programming Language :: Python :: 3.10
Requires-Dist: click (>=8.1.3,<9.0.0)
